brain_modeling_ecosystem/__init__.py
brain_modeling_ecosystem-2025.5.4.dist-info/LICENSE
brain_modeling_ecosystem-2025.5.4.dist-info/METADATA
brain_modeling_ecosystem-2025.5.4.dist-info/WHEEL
brain_modeling_ecosystem-2025.5.4.dist-info/top_level.txt
brain_modeling_ecosystem-2025.5.4.dist-info/RECORD
