Metadata-Version: 2.1
Name: brain-modeling-ecosystem
Version: 2025.5.4
Summary: Brain Modeling Ecosystem.
Home-page: https://github.com/chaobrain/brain-modeling-ecosystem
Author: BrainEvent Developers
Author-email: Brain Modeling Ecosystem Developers <chao.brain@qq.com>
License: Apache-2.0 license
Project-URL: homepage, http://github.com/chaobrain/brain-modeling-ecosystem
Project-URL: repository, http://github.com/chaobrain/brain-modeling-ecosystem
Keywords: computational neuroscience,brain-inspired computation,brain dynamics programming
Classifier: Natural Language :: English
Classifier: Operating System :: OS Independent
Classifier: Development Status :: 4 - Beta
Classifier: Intended Audience :: Developers
Classifier: Intended Audience :: Science/Research
Classifier: Programming Language :: Python :: 3
Classifier: Programming Language :: Python :: 3.10
Classifier: Programming Language :: Python :: 3.11
Classifier: Programming Language :: Python :: 3.12
Classifier: Programming Language :: Python :: 3.13
Classifier: License :: OSI Approved :: Apache Software License
Classifier: Programming Language :: Python
Classifier: Topic :: Scientific/Engineering :: Bio-Informatics
Classifier: Topic :: Scientific/Engineering :: Mathematics
Classifier: Topic :: Scientific/Engineering :: Artificial Intelligence
Classifier: Topic :: Software Development :: Libraries
Requires-Python: >=3.10
License-File: LICENSE
Requires-Dist: numpy (>=1.15)
Requires-Dist: jax (>=0.4.35)
Requires-Dist: brainunit (>=0.0.10)
Requires-Dist: brainevent (>=0.0.1.post20250502)
Requires-Dist: brainstate (>=0.1.0.post20250501)
Requires-Dist: braincell (>=0.0.1.post20250216)
Requires-Dist: braintools (>=0.0.4.post20250423)
Provides-Extra: cpu
Requires-Dist: jaxlib ; extra == 'cpu'
Provides-Extra: cuda12
Requires-Dist: jaxlib[cuda12] ; extra == 'cuda12'
Provides-Extra: testing
Requires-Dist: pytest ; extra == 'testing'
Provides-Extra: tpu
Requires-Dist: jaxlib[tpu] ; extra == 'tpu'
